crud2csvdb/__init__.py
crud2csvdb/db_operations.py
crud2csvdb-0.0.2.dist-info/LICENCE
crud2csvdb-0.0.2.dist-info/METADATA
crud2csvdb-0.0.2.dist-info/WHEEL
crud2csvdb-0.0.2.dist-info/top_level.txt
crud2csvdb-0.0.2.dist-info/RECORD
